napari_multitask/__init__.py
napari_multitask/taskpanel.py
napari_multitask/taskview.py
napari_multitask/viewerstate.py
napari_multitask-0.0.2.dist-info/LICENSE
napari_multitask-0.0.2.dist-info/METADATA
napari_multitask-0.0.2.dist-info/WHEEL
napari_multitask-0.0.2.dist-info/entry_points.txt
napari_multitask-0.0.2.dist-info/top_level.txt
napari_multitask-0.0.2.dist-info/RECORD
