Metadata-Version: 2.1
Name: napari-multitask
Version: 0.0.2
Summary: Multitasking in napari
Home-page: UNKNOWN
Author: Hanjin Liu
Author-email: liuhanjin-sc@g.ecc.u-tokyo.ac.jp
License: BSD 3-Clause
Download-URL: https://github.com/hanjinliu/napari-multitask
Platform: UNKNOWN
Classifier: Framework :: napari
Classifier: Programming Language :: Python
Classifier: Programming Language :: Python :: 3
Classifier: Programming Language :: Python :: 3.7
Classifier: Programming Language :: Python :: 3.8
Classifier: Programming Language :: Python :: 3.9
Requires-Python: >=3.8
License-File: LICENSE
Requires-Dist: magic-class (>=0.5.11)
